cdp_agentkit_core/__init__.py
cdp_agentkit_core/actions/__init__.py
cdp_agentkit_core/actions/cdp_action.py
cdp_agentkit_core/actions/constants.py
cdp_agentkit_core/actions/defi/__init__.py
cdp_agentkit_core/actions/deploy_nft.py
cdp_agentkit_core/actions/deploy_token.py
cdp_agentkit_core/actions/get_balance.py
cdp_agentkit_core/actions/get_balance_nft.py
cdp_agentkit_core/actions/get_wallet_details.py
cdp_agentkit_core/actions/mint_nft.py
cdp_agentkit_core/actions/morpho/__init__.py
cdp_agentkit_core/actions/morpho/constants.py
cdp_agentkit_core/actions/morpho/deposit.py
cdp_agentkit_core/actions/morpho/withdraw.py
cdp_agentkit_core/actions/pyth/__init__.py
cdp_agentkit_core/actions/pyth/fetch_price.py
cdp_agentkit_core/actions/pyth/fetch_price_feed_id.py
cdp_agentkit_core/actions/register_basename.py
cdp_agentkit_core/actions/request_faucet_funds.py
cdp_agentkit_core/actions/social/__init__.py
cdp_agentkit_core/actions/social/twitter/__init__.py
cdp_agentkit_core/actions/social/twitter/account_details.py
cdp_agentkit_core/actions/social/twitter/account_mentions.py
cdp_agentkit_core/actions/social/twitter/action.py
cdp_agentkit_core/actions/social/twitter/post_tweet.py
cdp_agentkit_core/actions/social/twitter/post_tweet_reply.py
cdp_agentkit_core/actions/trade.py
cdp_agentkit_core/actions/transfer.py
cdp_agentkit_core/actions/transfer_nft.py
cdp_agentkit_core/actions/utils.py
cdp_agentkit_core/actions/wow/__init__.py
cdp_agentkit_core/actions/wow/buy_token.py
cdp_agentkit_core/actions/wow/constants.py
cdp_agentkit_core/actions/wow/create_token.py
cdp_agentkit_core/actions/wow/sell_token.py
cdp_agentkit_core/actions/wow/uniswap/__init__.py
cdp_agentkit_core/actions/wow/uniswap/constants.py
cdp_agentkit_core/actions/wow/uniswap/index.py
cdp_agentkit_core/actions/wow/utils.py
cdp_agentkit_core/actions/wrap_eth.py
cdp_agentkit_core-0.0.10.dist-info/METADATA
cdp_agentkit_core-0.0.10.dist-info/WHEEL
cdp_agentkit_core-0.0.10.dist-info/RECORD
